timeflux_rasr/__init__.py
timeflux_rasr/estimators/__init__.py
timeflux_rasr/estimators/blending.py
timeflux_rasr/estimators/rasr.py
timeflux_rasr/helpers/__init__.py
timeflux_rasr/helpers/check_events.py
timeflux_rasr/helpers/config.py
timeflux_rasr/helpers/utils.py
timeflux_rasr/helpers/viz.py
timeflux_rasr-0.1.1.dist-info/LICENSE
timeflux_rasr-0.1.1.dist-info/METADATA
timeflux_rasr-0.1.1.dist-info/WHEEL
timeflux_rasr-0.1.1.dist-info/top_level.txt
timeflux_rasr-0.1.1.dist-info/RECORD
